[
  {
    "id": 23,
    "word": "adequate",
    "phonetic": "/ˈædɪkwət/",
    "pos": "adj.",
    "meaning": "足够的/合格的",
    "example": "The shelter provides adequate protection from storms.",
    "exampleCn": "这个避难所能提供足够的风暴防护。",
    "category": "cet4",
    "categories": [
      "cet4",
      "toefl"
    ],
    "level": "4",
    "list": "8"
  },
  {
    "id": 258,
    "word": "blast",
    "phonetic": "/blæst/",
    "pos": "n./v.",
    "meaning": "爆炸/强风/猛烈抨击/炸开",
    "example": "The blast damaged several buildings.",
    "exampleCn": "爆炸损坏了几栋建筑。",
    "category": "daily",
    "categories": [
      "daily",
      "toefl"
    ],
    "level": "4",
    "list": "8"
  },
  {
    "id": 410,
    "word": "chamber",
    "phonetic": "/ˈtʃeɪmbər/",
    "pos": "n.",
    "meaning": "房间/室/议院",
    "example": "The fossils were stored in a cool chamber.",
    "exampleCn": "化石被存放在一个凉爽的房间里。",
    "category": "medical",
    "categories": [
      "medical",
      "toefl"
    ],
    "level": "4",
    "list": "8"
  },
  {
    "id": 439,
    "word": "chill",
    "phonetic": "/tʃɪl/",
    "pos": "n./v./adj.",
    "meaning": "寒意/使变冷/放松/寒冷的",
    "example": "A sudden chill filled the room.",
    "exampleCn": "一阵突如其来的寒意充满了房间。",
    "category": "food",
    "categories": [
      "food",
      "toefl"
    ],
    "level": "4",
    "list": "8"
  },
  {
    "id": 2082,
    "word": "unequaled",
    "phonetic": "/ʌnˈiːkwəld/",
    "pos": "adj.",
    "meaning": "无与伦比的/无敌的",
    "example": "The team's dedication was unequaled in the competition.",
    "exampleCn": "这支队伍的投入在比赛中是无与伦比的。",
    "category": "toefl",
    "categories": [
      "toefl"
    ],
    "level": "4",
    "list": "8"
  },
  {
    "id": 2083,
    "word": "immune",
    "phonetic": "/ɪˈmjuːn/",
    "pos": "adj./n.",
    "meaning": "免疫的/不受影响的/免疫者",
    "example": "Some animals are immune to certain diseases.",
    "exampleCn": "一些动物对某些疾病有免疫力。",
    "category": "toefl",
    "categories": [
      "toefl"
    ],
    "level": "4",
    "list": "8"
  },
  {
    "id": 2084,
    "word": "institution",
    "phonetic": "/ˌɪnstɪˈtuːʃn/",
    "pos": "n.",
    "meaning": "机构/制度/惯例",
    "example": "The museum is an important cultural institution.",
    "exampleCn": "这座博物馆是一个重要的文化机构。",
    "category": "toefl",
    "categories": [
      "toefl"
    ],
    "level": "4",
    "list": "8"
  },
  {
    "id": 2085,
    "word": "argumentative",
    "phonetic": "/ˌɑːrɡjuˈmentətɪv/",
    "pos": "adj.",
    "meaning": "好争论的/议论文式的",
    "example": "The essay has a clear argumentative structure.",
    "exampleCn": "这篇文章有清晰的议论文结构。",
    "category": "toefl",
    "categories": [
      "toefl"
    ],
    "level": "4",
    "list": "8"
  },
  {
    "id": 2086,
    "word": "renewable",
    "phonetic": "/rɪˈnuːəbl/",
    "pos": "adj.",
    "meaning": "可再生的/可更新的",
    "example": "Solar power is a renewable energy source.",
    "exampleCn": "太阳能是一种可再生能源。",
    "category": "toefl",
    "categories": [
      "toefl"
    ],
    "level": "4",
    "list": "8"
  },
  {
    "id": 2087,
    "word": "nonetheless",
    "phonetic": "/ˌnʌnðəˈles/",
    "pos": "adv.",
    "meaning": "尽管如此/然而",
    "example": "The task was difficult; nonetheless, she finished it on time.",
    "exampleCn": "这项任务很难；尽管如此，她还是按时完成了。",
    "category": "toefl",
    "categories": [
      "toefl"
    ],
    "level": "4",
    "list": "8"
  },
  {
    "id": 2088,
    "word": "stun",
    "phonetic": "/stʌn/",
    "pos": "v.",
    "meaning": "使震惊/使昏迷",
    "example": "The discovery stunned the researchers.",
    "exampleCn": "这个发现使研究人员震惊。",
    "category": "toefl",
    "categories": [
      "toefl"
    ],
    "level": "4",
    "list": "8"
  },
  {
    "id": 2089,
    "word": "harshness",
    "phonetic": "/ˈhɑːrʃnəs/",
    "pos": "n.",
    "meaning": "严酷/刺耳/粗糙",
    "example": "The harshness of the desert climate limits plant growth.",
    "exampleCn": "沙漠气候的严酷限制了植物生长。",
    "category": "toefl",
    "categories": [
      "toefl"
    ],
    "level": "4",
    "list": "8"
  },
  {
    "id": 2090,
    "word": "fiber",
    "phonetic": "/ˈfaɪbər/",
    "pos": "n.",
    "meaning": "纤维/纤维质",
    "example": "Cotton fiber is used to make many types of cloth.",
    "exampleCn": "棉纤维被用来制作许多种布料。",
    "category": "toefl",
    "categories": [
      "toefl"
    ],
    "level": "4",
    "list": "8"
  },
  {
    "id": 2091,
    "word": "immigrant",
    "phonetic": "/ˈɪmɪɡrənt/",
    "pos": "n./adj.",
    "meaning": "移民/移民的",
    "example": "The city has a large immigrant population.",
    "exampleCn": "这座城市有大量移民人口。",
    "category": "toefl",
    "categories": [
      "toefl"
    ],
    "level": "4",
    "list": "8"
  },
  {
    "id": 2092,
    "word": "distress",
    "phonetic": "/dɪˈstres/",
    "pos": "n./v.",
    "meaning": "痛苦/危难/使痛苦",
    "example": "The rescue team answered the hikers' distress call.",
    "exampleCn": "救援队回应了徒步者的求救信号。",
    "category": "toefl",
    "categories": [
      "toefl"
    ],
    "level": "4",
    "list": "8"
  },
  {
    "id": 2093,
    "word": "filter",
    "phonetic": "/ˈfɪltər/",
    "pos": "n./v.",
    "meaning": "过滤器/筛选/过滤",
    "example": "The machine uses a filter to clean the water.",
    "exampleCn": "这台机器用过滤器净化水。",
    "category": "toefl",
    "categories": [
      "toefl"
    ],
    "level": "4",
    "list": "8"
  },
  {
    "id": 2094,
    "word": "composer",
    "phonetic": "/kəmˈpoʊzər/",
    "pos": "n.",
    "meaning": "作曲家",
    "example": "The composer wrote music for films and concerts.",
    "exampleCn": "这位作曲家为电影和音乐会创作音乐。",
    "category": "toefl",
    "categories": [
      "toefl"
    ],
    "level": "4",
    "list": "8"
  },
  {
    "id": 2095,
    "word": "utilization",
    "phonetic": "/ˌjuːtələˈzeɪʃn/",
    "pos": "n.",
    "meaning": "利用/使用",
    "example": "Better utilization of resources can reduce waste.",
    "exampleCn": "更好地利用资源可以减少浪费。",
    "category": "toefl",
    "categories": [
      "toefl"
    ],
    "level": "4",
    "list": "8"
  },
  {
    "id": 2096,
    "word": "stellar",
    "phonetic": "/ˈstelər/",
    "pos": "adj.",
    "meaning": "恒星的/极好的",
    "example": "The telescope captured images of stellar clouds.",
    "exampleCn": "望远镜拍摄到了恒星云的图像。",
    "category": "toefl",
    "categories": [
      "toefl"
    ],
    "level": "4",
    "list": "8"
  },
  {
    "id": 2097,
    "word": "enlist",
    "phonetic": "/ɪnˈlɪst/",
    "pos": "v.",
    "meaning": "入伍/征募/争取帮助",
    "example": "The organization tried to enlist volunteers for the project.",
    "exampleCn": "该组织试图为这个项目招募志愿者。",
    "category": "toefl",
    "categories": [
      "toefl"
    ],
    "level": "4",
    "list": "8"
  },
  {
    "id": 2098,
    "word": "formulate",
    "phonetic": "/ˈfɔːrmjuleɪt/",
    "pos": "v.",
    "meaning": "制定/构想/明确表达",
    "example": "Scientists must formulate a clear hypothesis.",
    "exampleCn": "科学家必须提出一个清晰的假设。",
    "category": "toefl",
    "categories": [
      "toefl"
    ],
    "level": "4",
    "list": "8"
  },
  {
    "id": 2099,
    "word": "mute",
    "phonetic": "/mjuːt/",
    "pos": "adj./v./n.",
    "meaning": "沉默的/减弱声音/使静音/哑巴",
    "example": "He pressed the button to mute the video.",
    "exampleCn": "他按下按钮将视频静音。",
    "category": "toefl",
    "categories": [
      "toefl"
    ],
    "level": "4",
    "list": "8"
  },
  {
    "id": 2100,
    "word": "intermediate",
    "phonetic": "/ˌɪntərˈmiːdiət/",
    "pos": "adj./n.",
    "meaning": "中级的/中间的/中间体",
    "example": "This book is suitable for intermediate learners.",
    "exampleCn": "这本书适合中级学习者。",
    "category": "toefl",
    "categories": [
      "toefl"
    ],
    "level": "4",
    "list": "8"
  },
  {
    "id": 2101,
    "word": "plum",
    "phonetic": "/plʌm/",
    "pos": "n./adj.",
    "meaning": "李子/紫红色/极好的",
    "example": "The plum tree blooms early in spring.",
    "exampleCn": "李子树在早春开花。",
    "category": "toefl",
    "categories": [
      "toefl"
    ],
    "level": "4",
    "list": "8"
  },
  {
    "id": 2102,
    "word": "wreck",
    "phonetic": "/rek/",
    "pos": "n./v.",
    "meaning": "残骸/失事/破坏",
    "example": "The storm left the boat a wreck.",
    "exampleCn": "暴风雨使那艘船成了残骸。",
    "category": "toefl",
    "categories": [
      "toefl"
    ],
    "level": "4",
    "list": "8"
  },
  {
    "id": 2103,
    "word": "sensory",
    "phonetic": "/ˈsensəri/",
    "pos": "adj.",
    "meaning": "感觉的/感官的",
    "example": "The experiment tested sensory responses to light.",
    "exampleCn": "这个实验测试了对光的感官反应。",
    "category": "toefl",
    "categories": [
      "toefl"
    ],
    "level": "4",
    "list": "8"
  },
  {
    "id": 2104,
    "word": "irresistible",
    "phonetic": "/ˌɪrɪˈzɪstəbl/",
    "pos": "adj.",
    "meaning": "不可抗拒的/极有吸引力的",
    "example": "The smell of fresh bread was irresistible.",
    "exampleCn": "新鲜面包的香味令人无法抗拒。",
    "category": "toefl",
    "categories": [
      "toefl"
    ],
    "level": "4",
    "list": "8"
  },
  {
    "id": 2105,
    "word": "showcase",
    "phonetic": "/ˈʃoʊkeɪs/",
    "pos": "n./v.",
    "meaning": "展示柜/展示",
    "example": "The festival will showcase local art.",
    "exampleCn": "这个节日将展示当地艺术。",
    "category": "toefl",
    "categories": [
      "toefl"
    ],
    "level": "4",
    "list": "8"
  },
  {
    "id": 2106,
    "word": "unobtainable",
    "phonetic": "/ˌʌnəbˈteɪnəbl/",
    "pos": "adj.",
    "meaning": "得不到的/无法获得的",
    "example": "The original document is now unobtainable.",
    "exampleCn": "原始文件现在已经无法获得。",
    "category": "toefl",
    "categories": [
      "toefl"
    ],
    "level": "4",
    "list": "8"
  },
  {
    "id": 2107,
    "word": "ration",
    "phonetic": "/ˈræʃn/",
    "pos": "n./v.",
    "meaning": "定量/配给/限量供应",
    "example": "Food was rationed during the emergency.",
    "exampleCn": "紧急时期食物被限量供应。",
    "category": "toefl",
    "categories": [
      "toefl"
    ],
    "level": "4",
    "list": "8"
  },
  {
    "id": 2108,
    "word": "moderate",
    "phonetic": "/ˈmɑːdərət/",
    "pos": "adj./n./v.",
    "meaning": "适度的/温和的/中间派/缓和",
    "example": "Moderate exercise can improve health.",
    "exampleCn": "适度运动可以改善健康。",
    "category": "toefl",
    "categories": [
      "toefl"
    ],
    "level": "4",
    "list": "8"
  },
  {
    "id": 2109,
    "word": "peak",
    "phonetic": "/piːk/",
    "pos": "n./adj./v.",
    "meaning": "顶峰/最高的/达到顶点",
    "example": "Tourism reaches its peak in summer.",
    "exampleCn": "旅游业在夏季达到高峰。",
    "category": "toefl",
    "categories": [
      "toefl"
    ],
    "level": "4",
    "list": "8"
  },
  {
    "id": 2110,
    "word": "hormone",
    "phonetic": "/ˈhɔːrmoʊn/",
    "pos": "n.",
    "meaning": "激素/荷尔蒙",
    "example": "This hormone helps control growth.",
    "exampleCn": "这种激素有助于控制生长。",
    "category": "toefl",
    "categories": [
      "toefl"
    ],
    "level": "4",
    "list": "8"
  },
  {
    "id": 2111,
    "word": "per capita",
    "phonetic": "/pər ˈkæpɪtə/",
    "pos": "adv./adj.",
    "meaning": "按人均计算/人均的",
    "example": "The country has a high income per capita.",
    "exampleCn": "这个国家的人均收入很高。",
    "category": "toefl",
    "categories": [
      "toefl"
    ],
    "level": "4",
    "list": "8"
  },
  {
    "id": 2112,
    "word": "conversion",
    "phonetic": "/kənˈvɜːrʒn/",
    "pos": "n.",
    "meaning": "转变/转换/换算",
    "example": "The conversion of sunlight into energy is essential to plants.",
    "exampleCn": "阳光转化为能量对植物至关重要。",
    "category": "toefl",
    "categories": [
      "toefl"
    ],
    "level": "4",
    "list": "8"
  },
  {
    "id": 2113,
    "word": "miscalculate",
    "phonetic": "/ˌmɪsˈkælkjuleɪt/",
    "pos": "v.",
    "meaning": "误算/判断错误",
    "example": "They miscalculated the cost of the project.",
    "exampleCn": "他们误算了项目成本。",
    "category": "toefl",
    "categories": [
      "toefl"
    ],
    "level": "4",
    "list": "8"
  },
  {
    "id": 2114,
    "word": "recurrence",
    "phonetic": "/rɪˈkɜːrəns/",
    "pos": "n.",
    "meaning": "复发/再次发生/循环",
    "example": "The recurrence of floods worried the villagers.",
    "exampleCn": "洪水的再次发生让村民们担忧。",
    "category": "toefl",
    "categories": [
      "toefl"
    ],
    "level": "4",
    "list": "8"
  },
  {
    "id": 2115,
    "word": "ironic",
    "phonetic": "/aɪˈrɑːnɪk/",
    "pos": "adj.",
    "meaning": "讽刺的/出乎意料的",
    "example": "It was ironic that the fire station burned down.",
    "exampleCn": "消防站被烧毁这件事很讽刺。",
    "category": "toefl",
    "categories": [
      "toefl"
    ],
    "level": "4",
    "list": "8"
  },
  {
    "id": 2116,
    "word": "progression",
    "phonetic": "/prəˈɡreʃn/",
    "pos": "n.",
    "meaning": "进展/发展/连续",
    "example": "The chart shows the progression of the disease.",
    "exampleCn": "这张图显示了疾病的发展过程。",
    "category": "toefl",
    "categories": [
      "toefl"
    ],
    "level": "4",
    "list": "8"
  },
  {
    "id": 2117,
    "word": "mimic",
    "phonetic": "/ˈmɪmɪk/",
    "pos": "v./n./adj.",
    "meaning": "模仿/模仿者/模拟的",
    "example": "Some insects mimic leaves to avoid predators.",
    "exampleCn": "一些昆虫模仿树叶来躲避捕食者。",
    "category": "toefl",
    "categories": [
      "toefl"
    ],
    "level": "4",
    "list": "8"
  },
  {
    "id": 2118,
    "word": "hallmark",
    "phonetic": "/ˈhɔːlmɑːrk/",
    "pos": "n.",
    "meaning": "标志/特点",
    "example": "Clear evidence is a hallmark of good research.",
    "exampleCn": "清晰的证据是优秀研究的标志。",
    "category": "toefl",
    "categories": [
      "toefl"
    ],
    "level": "4",
    "list": "8"
  },
  {
    "id": 2119,
    "word": "forehead",
    "phonetic": "/ˈfɔːrhed/",
    "pos": "n.",
    "meaning": "额头",
    "example": "She wiped the sweat from her forehead.",
    "exampleCn": "她擦掉额头上的汗。",
    "category": "toefl",
    "categories": [
      "toefl"
    ],
    "level": "4",
    "list": "8"
  },
  {
    "id": 2120,
    "word": "dictate",
    "phonetic": "/ˈdɪkteɪt/",
    "pos": "v./n.",
    "meaning": "命令/决定/口述/命令",
    "example": "Climate can dictate the types of crops grown in a region.",
    "exampleCn": "气候会决定一个地区种植的作物种类。",
    "category": "toefl",
    "categories": [
      "toefl"
    ],
    "level": "4",
    "list": "8"
  },
  {
    "id": 2121,
    "word": "endeavor",
    "phonetic": "/ɪnˈdevər/",
    "pos": "n./v.",
    "meaning": "努力/尝试/努力做",
    "example": "The expedition was a major scientific endeavor.",
    "exampleCn": "这次探险是一项重大的科学努力。",
    "category": "toefl",
    "categories": [
      "toefl"
    ],
    "level": "4",
    "list": "8"
  },
  {
    "id": 2122,
    "word": "longitude",
    "phonetic": "/ˈlɑːndʒɪtuːd/",
    "pos": "n.",
    "meaning": "经度",
    "example": "Longitude is used to measure position east or west.",
    "exampleCn": "经度用于测量东西方向的位置。",
    "category": "toefl",
    "categories": [
      "toefl"
    ],
    "level": "4",
    "list": "8"
  },
  {
    "id": 2123,
    "word": "drama",
    "phonetic": "/ˈdrɑːmə/",
    "pos": "n.",
    "meaning": "戏剧/戏剧性事件",
    "example": "Ancient Greek drama influenced later literature.",
    "exampleCn": "古希腊戏剧影响了后来的文学。",
    "category": "toefl",
    "categories": [
      "toefl"
    ],
    "level": "4",
    "list": "8"
  },
  {
    "id": 2124,
    "word": "infect",
    "phonetic": "/ɪnˈfekt/",
    "pos": "v.",
    "meaning": "感染/传染",
    "example": "The virus can infect cells quickly.",
    "exampleCn": "这种病毒能迅速感染细胞。",
    "category": "toefl",
    "categories": [
      "toefl"
    ],
    "level": "4",
    "list": "8"
  },
  {
    "id": 2125,
    "word": "symptom",
    "phonetic": "/ˈsɪmptəm/",
    "pos": "n.",
    "meaning": "症状/征兆",
    "example": "A fever can be a symptom of infection.",
    "exampleCn": "发烧可能是感染的症状。",
    "category": "toefl",
    "categories": [
      "toefl"
    ],
    "level": "4",
    "list": "8"
  },
  {
    "id": 2126,
    "word": "ceremonial",
    "phonetic": "/ˌserəˈmoʊniəl/",
    "pos": "adj.",
    "meaning": "仪式的/礼仪的",
    "example": "The crown has mainly ceremonial importance.",
    "exampleCn": "这顶王冠主要具有仪式意义。",
    "category": "toefl",
    "categories": [
      "toefl"
    ],
    "level": "4",
    "list": "8"
  },
  {
    "id": 2127,
    "word": "latitude",
    "phonetic": "/ˈlætɪtuːd/",
    "pos": "n.",
    "meaning": "纬度/自由度",
    "example": "Latitude affects climate and daylight hours.",
    "exampleCn": "纬度会影响气候和日照时间。",
    "category": "toefl",
    "categories": [
      "toefl"
    ],
    "level": "4",
    "list": "8"
  },
  {
    "id": 2128,
    "word": "sacred",
    "phonetic": "/ˈseɪkrɪd/",
    "pos": "adj.",
    "meaning": "神圣的/受尊敬的",
    "example": "The temple is considered sacred by local people.",
    "exampleCn": "这座寺庙被当地人视为神圣之地。",
    "category": "toefl",
    "categories": [
      "toefl"
    ],
    "level": "4",
    "list": "8"
  },
  {
    "id": 2129,
    "word": "taxation",
    "phonetic": "/tækˈseɪʃn/",
    "pos": "n.",
    "meaning": "税收/征税",
    "example": "Taxation provides money for public services.",
    "exampleCn": "税收为公共服务提供资金。",
    "category": "toefl",
    "categories": [
      "toefl"
    ],
    "level": "4",
    "list": "8"
  },
  {
    "id": 2130,
    "word": "gross",
    "phonetic": "/ɡroʊs/",
    "pos": "adj./n./v.",
    "meaning": "总的/粗俗的/严重的/总额/总共赚得",
    "example": "The report listed the company's gross income.",
    "exampleCn": "报告列出了公司的总收入。",
    "category": "toefl",
    "categories": [
      "toefl"
    ],
    "level": "4",
    "list": "8"
  },
  {
    "id": 2131,
    "word": "vibrant",
    "phonetic": "/ˈvaɪbrənt/",
    "pos": "adj.",
    "meaning": "充满活力的/鲜艳的/响亮的",
    "example": "The market was full of vibrant colors and sounds.",
    "exampleCn": "市场充满了鲜艳的色彩和热闹的声音。",
    "category": "toefl",
    "categories": [
      "toefl"
    ],
    "level": "4",
    "list": "8"
  },
  {
    "id": 2132,
    "word": "consequence",
    "phonetic": "/ˈkɑːnsɪkwens/",
    "pos": "n.",
    "meaning": "结果/后果/重要性",
    "example": "Pollution is a serious consequence of rapid industrial growth.",
    "exampleCn": "污染是工业快速增长的严重后果。",
    "category": "toefl",
    "categories": [
      "toefl"
    ],
    "level": "4",
    "list": "8"
  },
  {
    "id": 2133,
    "word": "compensate",
    "phonetic": "/ˈkɑːmpenseɪt/",
    "pos": "v.",
    "meaning": "补偿/弥补",
    "example": "The company agreed to compensate the workers.",
    "exampleCn": "公司同意补偿工人。",
    "category": "toefl",
    "categories": [
      "toefl"
    ],
    "level": "4",
    "list": "8"
  },
  {
    "id": 2134,
    "word": "harmonious",
    "phonetic": "/hɑːrˈmoʊniəs/",
    "pos": "adj.",
    "meaning": "和谐的/协调的",
    "example": "The colors create a harmonious design.",
    "exampleCn": "这些颜色形成了和谐的设计。",
    "category": "toefl",
    "categories": [
      "toefl"
    ],
    "level": "4",
    "list": "8"
  },
  {
    "id": 2135,
    "word": "plumb",
    "phonetic": "/plʌm/",
    "pos": "v./adv./adj./n.",
    "meaning": "探测/完全地/垂直的/铅锤",
    "example": "Researchers tried to plumb the depths of the lake.",
    "exampleCn": "研究人员试图探测湖的深度。",
    "category": "toefl",
    "categories": [
      "toefl"
    ],
    "level": "4",
    "list": "8"
  },
  {
    "id": 2136,
    "word": "stimulate",
    "phonetic": "/ˈstɪmjuleɪt/",
    "pos": "v.",
    "meaning": "刺激/促进/激发",
    "example": "Light can stimulate plant growth.",
    "exampleCn": "光能促进植物生长。",
    "category": "toefl",
    "categories": [
      "toefl"
    ],
    "level": "4",
    "list": "8"
  },
  {
    "id": 2137,
    "word": "format",
    "phonetic": "/ˈfɔːrmæt/",
    "pos": "n./v.",
    "meaning": "格式/版式/安排格式",
    "example": "Please save the file in the correct format.",
    "exampleCn": "请用正确的格式保存文件。",
    "category": "toefl",
    "categories": [
      "toefl"
    ],
    "level": "4",
    "list": "8"
  },
  {
    "id": 2138,
    "word": "practicality",
    "phonetic": "/ˌpræktɪˈkæləti/",
    "pos": "n.",
    "meaning": "实用性/实际情况",
    "example": "The plan was judged by its practicality.",
    "exampleCn": "这个计划根据其实用性进行评估。",
    "category": "toefl",
    "categories": [
      "toefl"
    ],
    "level": "4",
    "list": "8"
  },
  {
    "id": 2139,
    "word": "hay",
    "phonetic": "/heɪ/",
    "pos": "n.",
    "meaning": "干草",
    "example": "The farmer stored hay for the winter.",
    "exampleCn": "农民储存干草以备冬天使用。",
    "category": "toefl",
    "categories": [
      "toefl"
    ],
    "level": "4",
    "list": "8"
  },
  {
    "id": 2140,
    "word": "spill",
    "phonetic": "/spɪl/",
    "pos": "v./n.",
    "meaning": "溢出/洒出/泄露/溢出物",
    "example": "Be careful not to spill the chemicals.",
    "exampleCn": "小心不要洒出这些化学品。",
    "category": "toefl",
    "categories": [
      "toefl"
    ],
    "level": "4",
    "list": "8"
  },
  {
    "id": 2141,
    "word": "infinite",
    "phonetic": "/ˈɪnfɪnət/",
    "pos": "adj.",
    "meaning": "无限的/无穷的",
    "example": "The universe may contain an infinite number of stars.",
    "exampleCn": "宇宙可能包含无数恒星。",
    "category": "toefl",
    "categories": [
      "toefl"
    ],
    "level": "4",
    "list": "8"
  },
  {
    "id": 2142,
    "word": "inquire",
    "phonetic": "/ɪnˈkwaɪr/",
    "pos": "v.",
    "meaning": "询问/调查",
    "example": "Students may inquire about the program by email.",
    "exampleCn": "学生可以通过电子邮件询问这个项目。",
    "category": "toefl",
    "categories": [
      "toefl"
    ],
    "level": "4",
    "list": "8"
  },
  {
    "id": 2143,
    "word": "split",
    "phonetic": "/splɪt/",
    "pos": "v./n./adj.",
    "meaning": "分裂/分开/裂缝/分裂的",
    "example": "The river splits into two smaller streams.",
    "exampleCn": "这条河分成两条较小的溪流。",
    "category": "toefl",
    "categories": [
      "toefl"
    ],
    "level": "4",
    "list": "8"
  },
  {
    "id": 2144,
    "word": "merge",
    "phonetic": "/mɜːrdʒ/",
    "pos": "v.",
    "meaning": "合并/融合",
    "example": "The two companies decided to merge.",
    "exampleCn": "这两家公司决定合并。",
    "category": "toefl",
    "categories": [
      "toefl"
    ],
    "level": "4",
    "list": "8"
  },
  {
    "id": 2145,
    "word": "abbreviate",
    "phonetic": "/əˈbriːvieɪt/",
    "pos": "v.",
    "meaning": "缩写/缩短",
    "example": "The word 'doctor' is often abbreviated as 'Dr.'.",
    "exampleCn": "doctor 这个词常被缩写为 Dr.。",
    "category": "toefl",
    "categories": [
      "toefl"
    ],
    "level": "4",
    "list": "8"
  },
  {
    "id": 2146,
    "word": "vague",
    "phonetic": "/veɪɡ/",
    "pos": "adj.",
    "meaning": "模糊的/不明确的",
    "example": "His answer was too vague to be useful.",
    "exampleCn": "他的回答太模糊，没有什么帮助。",
    "category": "toefl",
    "categories": [
      "toefl"
    ],
    "level": "4",
    "list": "8"
  },
  {
    "id": 2147,
    "word": "ditch",
    "phonetic": "/dɪtʃ/",
    "pos": "n./v.",
    "meaning": "沟渠/抛弃/摆脱",
    "example": "Rainwater flowed through the ditch beside the road.",
    "exampleCn": "雨水流过路边的沟渠。",
    "category": "toefl",
    "categories": [
      "toefl"
    ],
    "level": "4",
    "list": "8"
  },
  {
    "id": 2148,
    "word": "respective",
    "phonetic": "/rɪˈspektɪv/",
    "pos": "adj.",
    "meaning": "各自的/分别的",
    "example": "The students returned to their respective classrooms.",
    "exampleCn": "学生们回到各自的教室。",
    "category": "toefl",
    "categories": [
      "toefl"
    ],
    "level": "4",
    "list": "8"
  },
  {
    "id": 2149,
    "word": "roast",
    "phonetic": "/roʊst/",
    "pos": "v./n./adj.",
    "meaning": "烤/烘烤/烤肉/烤制的",
    "example": "They roast coffee beans before grinding them.",
    "exampleCn": "他们在研磨咖啡豆之前先烘焙。",
    "category": "toefl",
    "categories": [
      "toefl"
    ],
    "level": "4",
    "list": "8"
  },
  {
    "id": 2150,
    "word": "tablet",
    "phonetic": "/ˈtæblət/",
    "pos": "n.",
    "meaning": "药片/平板电脑/碑板",
    "example": "The doctor gave him a tablet for pain.",
    "exampleCn": "医生给了他一片止痛药。",
    "category": "toefl",
    "categories": [
      "toefl"
    ],
    "level": "4",
    "list": "8"
  },
  {
    "id": 2151,
    "word": "ray",
    "phonetic": "/reɪ/",
    "pos": "n.",
    "meaning": "光线/射线/一丝",
    "example": "A ray of sunlight entered the room.",
    "exampleCn": "一束阳光照进房间。",
    "category": "toefl",
    "categories": [
      "toefl"
    ],
    "level": "4",
    "list": "8"
  },
  {
    "id": 2152,
    "word": "barren",
    "phonetic": "/ˈbærən/",
    "pos": "adj.",
    "meaning": "贫瘠的/荒芜的/不结果实的",
    "example": "Few plants can survive in barren soil.",
    "exampleCn": "很少有植物能在贫瘠的土壤中生存。",
    "category": "toefl",
    "categories": [
      "toefl"
    ],
    "level": "4",
    "list": "8"
  },
  {
    "id": 2153,
    "word": "disgust",
    "phonetic": "/dɪsˈɡʌst/",
    "pos": "n./v.",
    "meaning": "厌恶/反感/使厌恶",
    "example": "The smell filled the room with disgust.",
    "exampleCn": "那股气味让房间里的人感到厌恶。",
    "category": "toefl",
    "categories": [
      "toefl"
    ],
    "level": "4",
    "list": "8"
  },
  {
    "id": 2154,
    "word": "mythic",
    "phonetic": "/ˈmɪθɪk/",
    "pos": "adj.",
    "meaning": "神话的/传奇般的",
    "example": "The hero has a mythic place in the culture.",
    "exampleCn": "这位英雄在文化中具有神话般的地位。",
    "category": "toefl",
    "categories": [
      "toefl"
    ],
    "level": "4",
    "list": "8"
  },
  {
    "id": 2155,
    "word": "shrinkage",
    "phonetic": "/ˈʃrɪŋkɪdʒ/",
    "pos": "n.",
    "meaning": "收缩/缩水/减少",
    "example": "The fabric showed shrinkage after washing.",
    "exampleCn": "这块布洗后出现了缩水。",
    "category": "toefl",
    "categories": [
      "toefl"
    ],
    "level": "4",
    "list": "8"
  },
  {
    "id": 2156,
    "word": "pesticide",
    "phonetic": "/ˈpestɪsaɪd/",
    "pos": "n.",
    "meaning": "杀虫剂/农药",
    "example": "Farmers used less pesticide to protect the soil.",
    "exampleCn": "农民减少使用农药来保护土壤。",
    "category": "toefl",
    "categories": [
      "toefl"
    ],
    "level": "4",
    "list": "8"
  },
  {
    "id": 2157,
    "word": "oversee",
    "phonetic": "/ˌoʊvərˈsiː/",
    "pos": "v.",
    "meaning": "监督/管理",
    "example": "A manager will oversee the entire project.",
    "exampleCn": "一位经理将监督整个项目。",
    "category": "toefl",
    "categories": [
      "toefl"
    ],
    "level": "4",
    "list": "8"
  },
  {
    "id": 2158,
    "word": "correspond",
    "phonetic": "/ˌkɔːrəˈspɑːnd/",
    "pos": "v.",
    "meaning": "符合/相对应/通信",
    "example": "The numbers correspond to the labels on the map.",
    "exampleCn": "这些数字与地图上的标签相对应。",
    "category": "toefl",
    "categories": [
      "toefl"
    ],
    "level": "4",
    "list": "8"
  },
  {
    "id": 2159,
    "word": "droplet",
    "phonetic": "/ˈdrɑːplət/",
    "pos": "n.",
    "meaning": "小滴/微滴",
    "example": "A water droplet formed on the leaf.",
    "exampleCn": "一滴水珠在叶子上形成。",
    "category": "toefl",
    "categories": [
      "toefl"
    ],
    "level": "4",
    "list": "8"
  },
  {
    "id": 2160,
    "word": "dissolve",
    "phonetic": "/dɪˈzɑːlv/",
    "pos": "v.",
    "meaning": "溶解/消失/解散",
    "example": "Salt will dissolve in warm water.",
    "exampleCn": "盐会溶解在温水中。",
    "category": "toefl",
    "categories": [
      "toefl"
    ],
    "level": "4",
    "list": "8"
  },
  {
    "id": 2161,
    "word": "rehearsal",
    "phonetic": "/rɪˈhɜːrsl/",
    "pos": "n.",
    "meaning": "排练/预演",
    "example": "The actors attended a rehearsal before the show.",
    "exampleCn": "演员们在演出前参加了排练。",
    "category": "toefl",
    "categories": [
      "toefl"
    ],
    "level": "4",
    "list": "8"
  },
  {
    "id": 2162,
    "word": "pore",
    "phonetic": "/pɔːr/",
    "pos": "n./v.",
    "meaning": "毛孔/小孔/仔细阅读",
    "example": "Sweat leaves the body through pores in the skin.",
    "exampleCn": "汗液通过皮肤上的毛孔排出体外。",
    "category": "toefl",
    "categories": [
      "toefl"
    ],
    "level": "4",
    "list": "8"
  },
  {
    "id": 2163,
    "word": "synthesis",
    "phonetic": "/ˈsɪnθəsɪs/",
    "pos": "n.",
    "meaning": "合成/综合",
    "example": "Photosynthesis is the synthesis of food using light.",
    "exampleCn": "光合作用是利用光合成食物的过程。",
    "category": "toefl",
    "categories": [
      "toefl"
    ],
    "level": "4",
    "list": "8"
  },
  {
    "id": 2164,
    "word": "improbable",
    "phonetic": "/ɪmˈprɑːbəbl/",
    "pos": "adj.",
    "meaning": "不大可能的/未必真实的",
    "example": "The story sounded improbable but was true.",
    "exampleCn": "这个故事听起来不太可能，但却是真的。",
    "category": "toefl",
    "categories": [
      "toefl"
    ],
    "level": "4",
    "list": "8"
  },
  {
    "id": 2165,
    "word": "reproduce",
    "phonetic": "/ˌriːprəˈduːs/",
    "pos": "v.",
    "meaning": "繁殖/复制/再现",
    "example": "Some plants reproduce through seeds.",
    "exampleCn": "一些植物通过种子繁殖。",
    "category": "toefl",
    "categories": [
      "toefl"
    ],
    "level": "4",
    "list": "8"
  },
  {
    "id": 2166,
    "word": "irrelevant",
    "phonetic": "/ɪˈreləvənt/",
    "pos": "adj.",
    "meaning": "不相关的/无关紧要的",
    "example": "The extra details were irrelevant to the argument.",
    "exampleCn": "这些额外细节与论点无关。",
    "category": "toefl",
    "categories": [
      "toefl"
    ],
    "level": "4",
    "list": "8"
  },
  {
    "id": 2167,
    "word": "catalyst",
    "phonetic": "/ˈkætəlɪst/",
    "pos": "n.",
    "meaning": "催化剂/促成因素",
    "example": "The new law acted as a catalyst for change.",
    "exampleCn": "这项新法律成为变革的催化剂。",
    "category": "toefl",
    "categories": [
      "toefl"
    ],
    "level": "4",
    "list": "8"
  },
  {
    "id": 2168,
    "word": "transit",
    "phonetic": "/ˈtrænzɪt/",
    "pos": "n./v.",
    "meaning": "运输/通行/通过",
    "example": "Public transit reduces traffic in large cities.",
    "exampleCn": "公共交通减少了大城市的交通拥堵。",
    "category": "toefl",
    "categories": [
      "toefl"
    ],
    "level": "4",
    "list": "8"
  },
  {
    "id": 2169,
    "word": "rib",
    "phonetic": "/rɪb/",
    "pos": "n./v.",
    "meaning": "肋骨/排骨/取笑",
    "example": "The rib cage protects the heart and lungs.",
    "exampleCn": "胸腔保护心脏和肺。",
    "category": "toefl",
    "categories": [
      "toefl"
    ],
    "level": "4",
    "list": "8"
  },
  {
    "id": 2170,
    "word": "spark",
    "phonetic": "/spɑːrk/",
    "pos": "n./v.",
    "meaning": "火花/引发/激发",
    "example": "A small spark started the fire.",
    "exampleCn": "一个小火花引发了火灾。",
    "category": "toefl",
    "categories": [
      "toefl"
    ],
    "level": "4",
    "list": "8"
  },
  {
    "id": 2171,
    "word": "merchant",
    "phonetic": "/ˈmɜːrtʃənt/",
    "pos": "n.",
    "meaning": "商人/批发商",
    "example": "The merchant sold cloth and spices.",
    "exampleCn": "这位商人出售布料和香料。",
    "category": "toefl",
    "categories": [
      "toefl"
    ],
    "level": "4",
    "list": "8"
  },
  {
    "id": 2172,
    "word": "encircle",
    "phonetic": "/ɪnˈsɜːrkl/",
    "pos": "v.",
    "meaning": "环绕/包围",
    "example": "Mountains encircle the valley.",
    "exampleCn": "群山环绕着这个山谷。",
    "category": "toefl",
    "categories": [
      "toefl"
    ],
    "level": "4",
    "list": "8"
  },
  {
    "id": 2173,
    "word": "glow",
    "phonetic": "/ɡloʊ/",
    "pos": "n./v.",
    "meaning": "光辉/发光/容光焕发",
    "example": "The lamps began to glow after sunset.",
    "exampleCn": "日落后，灯开始发光。",
    "category": "toefl",
    "categories": [
      "toefl"
    ],
    "level": "4",
    "list": "8"
  },
  {
    "id": 2174,
    "word": "plow",
    "phonetic": "/plaʊ/",
    "pos": "n./v.",
    "meaning": "犁/耕地",
    "example": "Farmers plow the fields before planting seeds.",
    "exampleCn": "农民在播种前犁地。",
    "category": "toefl",
    "categories": [
      "toefl"
    ],
    "level": "4",
    "list": "8"
  },
  {
    "id": 2175,
    "word": "windmill",
    "phonetic": "/ˈwɪndmɪl/",
    "pos": "n.",
    "meaning": "风车/风力磨坊",
    "example": "The old windmill was used to grind grain.",
    "exampleCn": "这座旧风车曾被用来磨谷物。",
    "category": "toefl",
    "categories": [
      "toefl"
    ],
    "level": "4",
    "list": "8"
  },
  {
    "id": 2176,
    "word": "ecologist",
    "phonetic": "/ɪˈkɑːlədʒɪst/",
    "pos": "n.",
    "meaning": "生态学家",
    "example": "The ecologist studied changes in the forest.",
    "exampleCn": "这位生态学家研究森林中的变化。",
    "category": "toefl",
    "categories": [
      "toefl"
    ],
    "level": "4",
    "list": "8"
  },
  {
    "id": 2177,
    "word": "asteroid",
    "phonetic": "/ˈæstərɔɪd/",
    "pos": "n.",
    "meaning": "小行星",
    "example": "An asteroid passed close to Earth.",
    "exampleCn": "一颗小行星从地球附近经过。",
    "category": "toefl",
    "categories": [
      "toefl"
    ],
    "level": "4",
    "list": "8"
  }
]
